livesettings/__init__.py
livesettings/forms.py
livesettings/functions.py
livesettings/models.py
livesettings/overrides.py
livesettings/signals.py
livesettings/test_urls.py
livesettings/tests.py
livesettings/urls.py
livesettings/utils.py
livesettings/values.py
livesettings/views.py
livesettings/locale/de/LC_MESSAGES/django.mo
livesettings/locale/de/LC_MESSAGES/django.po
livesettings/locale/en/LC_MESSAGES/django.mo
livesettings/locale/en/LC_MESSAGES/django.po
livesettings/locale/es/LC_MESSAGES/django.po
livesettings/locale/fr/LC_MESSAGES/django.mo
livesettings/locale/fr/LC_MESSAGES/django.po
livesettings/locale/he/LC_MESSAGES/django.mo
livesettings/locale/he/LC_MESSAGES/django.po
livesettings/locale/it/LC_MESSAGES/django.mo
livesettings/locale/it/LC_MESSAGES/django.po
livesettings/locale/ko/LC_MESSAGES/django.mo
livesettings/locale/ko/LC_MESSAGES/django.po
livesettings/locale/pl/LC_MESSAGES/django.mo
livesettings/locale/pl/LC_MESSAGES/django.po
livesettings/locale/pt_BR/LC_MESSAGES/django.mo
livesettings/locale/pt_BR/LC_MESSAGES/django.po
livesettings/locale/ru/LC_MESSAGES/django.mo
livesettings/locale/ru/LC_MESSAGES/django.po
livesettings/locale/sv/LC_MESSAGES/django.mo
livesettings/locale/sv/LC_MESSAGES/django.po
livesettings/locale/tr/LC_MESSAGES/django.mo
livesettings/locale/tr/LC_MESSAGES/django.po
livesettings/migrations/0001_initial.py
livesettings/migrations/__init__.py
livesettings/templates/livesettings/_admin_site_views.html
livesettings/templates/livesettings/group_settings.html
livesettings/templates/livesettings/site_settings.html
livesettings/templates/livesettings/text.txt
livesettings/templatetags/__init__.py
livesettings/templatetags/config_tags.py
djangoplicity_livesettings-1.4.17.dist-info/AUTHORS
djangoplicity_livesettings-1.4.17.dist-info/LICENSE
djangoplicity_livesettings-1.4.17.dist-info/METADATA
djangoplicity_livesettings-1.4.17.dist-info/WHEEL
djangoplicity_livesettings-1.4.17.dist-info/top_level.txt
djangoplicity_livesettings-1.4.17.dist-info/RECORD
