Metadata-Version: 2.1
Name: djangoplicity-livesettings
Version: 1.4.17
Summary: livesettings
Home-page: https://github.com/djangoplicity/djangoplicity-livesettings.git
Author: Bruce Kroeze
Author-email: bruce@ecomsmith.com
License: New BSD License
Download-URL: https://github.com/djangoplicity/djangoplicity-livesettings/archive/refs/tags/1.4.17.tar.gz
Platform: any
Classifier: Development Status :: 4 - Beta
Classifier: Environment :: Web Environment
Classifier: Intended Audience :: Developers
Classifier: License :: OSI Approved :: BSD License
Classifier: Operating System :: OS Independent
Classifier: Programming Language :: Python
Classifier: Framework :: Django
License-File: LICENSE
License-File: AUTHORS
